fairprice/__init__.py
fairprice/fairprice.py
fairprice-0.1.2.dist-info/LICENSE
fairprice-0.1.2.dist-info/METADATA
fairprice-0.1.2.dist-info/WHEEL
fairprice-0.1.2.dist-info/top_level.txt
fairprice-0.1.2.dist-info/RECORD
