Metadata-Version: 2.1
Name: fairprice
Version: 0.1.2
Summary: Balance the price of your products
Home-page: https://github.com/Style77/fairprice
Author: Joachim Hodana
Author-email: stylek777@gmail.com
License: MIT
Requires-Python: >=3.9
License-File: LICENSE
Requires-Dist: anyio ==4.0.0
Requires-Dist: black ==23.10.1
Requires-Dist: certifi ==2023.7.22
Requires-Dist: click ==8.1.7
Requires-Dist: colorama ==0.4.6
Requires-Dist: flake8 ==6.1.0
Requires-Dist: h11 ==0.14.0
Requires-Dist: httpcore ==1.0.1
Requires-Dist: httpx ==0.25.1
Requires-Dist: idna ==3.4
Requires-Dist: isort ==5.12.0
Requires-Dist: mccabe ==0.7.0
Requires-Dist: mypy ==1.6.1
Requires-Dist: mypy-extensions ==1.0.0
Requires-Dist: numpy ==1.26.1
Requires-Dist: packaging ==23.2
Requires-Dist: pandas ==2.1.2
Requires-Dist: pandas-stubs ==2.1.1.230928
Requires-Dist: pathspec ==0.11.2
Requires-Dist: platformdirs ==3.11.0
Requires-Dist: pycodestyle ==2.11.1
Requires-Dist: pyflakes ==3.1.0
Requires-Dist: python-dateutil ==2.8.2
Requires-Dist: python-dotenv ==1.0.0
Requires-Dist: pytz ==2023.3.post1
Requires-Dist: six ==1.16.0
Requires-Dist: sniffio ==1.3.0
Requires-Dist: types-pytz ==2023.3.1.1
Requires-Dist: types-setuptools ==68.2.0.0
Requires-Dist: typing-extensions ==4.8.0
Requires-Dist: tzdata ==2023.3
